owlshell/__init__.py
owlshell-0.0.4.dist-info/METADATA
owlshell-0.0.4.dist-info/WHEEL
owlshell-0.0.4.dist-info/top_level.txt
owlshell-0.0.4.dist-info/RECORD
