Metadata-Version: 2.1
Name: owlshell
Version: 0.0.4
Summary: A tool to use the OS functions and SEE AN ASCII ART OWL!
Home-page: https://github.com/Sovenok-Hacker/owlshell
Author: Sovenok-Hacker
Author-email: artemka.hvsotov@yandex.ru
License: UNKNOWN
Platform: UNKNOWN
Requires-Python: >=3.6
